MANIFEST.in
README.rst
setup.py
bin/pychimp
pychimp/__init__.py
pychimp.egg-info/PKG-INFO
pychimp.egg-info/SOURCES.txt
pychimp.egg-info/dependency_links.txt
pychimp.egg-info/not-zip-safe
pychimp.egg-info/requires.txt
pychimp.egg-info/top_level.txt