Metadata-Version: 1.2
Name: pychimp
Version: 0.0.1
Summary: A tool for shell command execution
Home-page: https://github.com/fusionstackio/pychimp
Author: Zile Rehman
Author-email: rehmanz@yahoo.com
License: MIT
Keywords: shell commands execution bash
Platform: UNKNOWN
Classifier: Development Status :: 1 - Planning
Classifier: Programming Language :: Python :: 3.4
Requires-Python: >=3.5
